kanc
