Metadata-Version: 1.0
Name: kanc
Version: 0.1.2
Summary: Simple Kanboard CUI client
Home-page: https://github.com/yuichi1004/kanc
Author: Yuichi Murata
Author-email: yuichi1004@gmail.com
License: MIT
Download-URL: https://github.com/yuichi1004/kanc/archive/v0.1.2.tar.gz
Platform: UNKNOWN
